{
  "tile_size": 256,
  "score":1,
  "workspace": ["start"],
  "toolbox": [
    "move_up",
    "move_down",
    "move_right",
    "move_left"
  ],
  "map": [
    ".#...#...",
    "....#.#..",
    "..#....#.",
    ".........",
    "..#d.a#..",
    ".a...#.a.",
    ".#.#.....",
    "......##.",
    "...#..%.."
  ],
  "extra":[{
    "x": 5,
    "y": 4,
    "img":"clover1"
  }, {
    "x": 1,
    "y": 5,
    "img":"clover2"
  }, {
    "x": 7,
    "y": 5,
    "img":"clover3"
  }, {
    "x": 6,
    "y": 8,
    "img":"clover4"
  }],
  "tutorial": [{
    "msg:ko": "토드는 규칙찾기 놀이를 하고 싶어. 빈칸에 들어갈 클로버 모양을 찾아가보자.",
    "msg:en": "Tod want to play the pattern problem. Find the shape of clover in the blank.",
    "img": [{
      "src": "/img/c5/clovers/clover3.png",
      "style": "width:25%"
    }, {
      "src": "/img/c5/clovers/clover2.png",
      "style": "width:25%"
    }, {
      "src": "/img/c5/clovers/clover1.png",
      "style": "width:25%"
    }, {
      "src": "/img/c5/clovers/clover0.png",
      "style": "width:25%"
    }]
  }],
  "goal": {
    "msg:ko": "빈칸에 들어갈 클로버 모양을 찾아가보자.",
    "msg:en": "Find the shape of clover in the blank.",
    "img": [{
      "src": "/img/c5/clovers/clover3.png",
      "style": "width:25%"
    }, {
      "src": "/img/c5/clovers/clover2.png",
      "style": "width:25%"
    }, {
      "src": "/img/c5/clovers/clover1.png",
      "style": "width:25%"
    }, {
      "src": "/img/c5/clovers/clover0.png",
      "style": "width:25%"
    }]
  },
  "success": [{
    "msg:ko": "성공! 참 잘했어요~",
    "msg:en": "Success! Good Job!",
    "img" : "/img/c5/clovers/clover4.png",
    "link": "c5_w1/8"
  }]
}
