{
  "tile_size": 32,
  "render": "pixel",
  "toolbox": [
    "move_up",
    "move_down",
    "move_left",
    "move_right"
  ],
  "map": [
    ".xxxxxxxxx.",
    "y.........y",
    "y....i....y",
    "y. ....i..y",
    "yi........y",
    "y...i.....y",
    "y....%....y",
    "y....u....y",
    "y.........y",
    "y.........y",
    ".xxxxxxxxx."
  ],
  "tutorial": [{
    "msg": "안녕! 난 무무라고 해",
    "img": "/img/999.png"
  }, {
    "msg": "공주님에게 고백하러 간다면서? 멋있다!",
    "img": "/img/999.png"
  }, {
    "msg": "앞으로 내가 도와줄테니까 설명을 잘 듣고 움직여봐!",
    "img": "/img/999.png"
  }, {
    "msg": "자 우선 위로 가는 방법을 배워볼까?",
    "img": "/img/999.png"
  }, {
    "msg": "↑위로 이동 블록을 꾹 누른상태에서 시작하면 블록 아래로 움직인후에 놓아보자!",
    "img": "/img/999.png"
  }]
}
