{
  "type": "world",
  "view_size": 8,
  "tile_size": 50,
  "render": "pixel",
  "toolbox": [],
  "map": [
    ".##########################.",
    "#......#..#....%.....%..#...",
    "#......#...%.....%.....%#...",
    "#.....#.u.#############.####",
    "#......#..#....%.....%......",
    "#......#..#..%...%......%...",
    ".##########################."
  ],
  "extra": [{
    "x": 11,
    "y": 2,
    "link": "7-2jack-food/1"
  },  {
    "x": 15,
    "y": 1,
    "link": "7-2jack-food/2"
  },  {
    "x": 17,
    "y": 2,
    "link": "7-2jack-food/3"
  },  {
    "x": 21,
    "y": 1,
    "link": "7-2jack-food/4"
  },  {
    "x": 23,
    "y": 2,
    "link": "7-2jack-food/5"
  },  {
    "x": 13,
    "y": 5,
    "link": "7-2jack-food/10"
  },  {
    "x": 15,
    "y": 4,
    "link": "7-2jack-food/9"
  },  {
    "x": 17,
    "y": 5,
    "link": "7-2jack-food/8"
  },  {
    "x": 21,
    "y": 4,
    "link": "7-2jack-food/7"
  },  {
    "x": 24,
    "y": 5,
    "link": "7-2jack-food/6"
  },  {
    "img":"baby",
    "x": 27,
    "y": 3,
    "obstacle": false,
    "link": "7-3jack-direction/index",
    "min_score": 15
  },  {
    "x": 10,
    "y": 1,
    "img":"normal",
    "obstacle": false,
    "tutorial": [{
      "msg": "먹이 1개 얻을 수 있어!",
      "img": "/img/guide/normal.png"
    }]
  },  {
    "x": 10,
    "y": 5,
    "img":"hard",
    "obstacle": false,
    "tutorial": [{
      "msg": "먹이 2개 얻을 수 있어!",
      "img": "/img/guide/hard.png"
    }]

  }],
  "tutorial": [{
    "msg": "참새 짹스패로우는 "
  }, {
    "msg": "아기새들을 위해서 먹이를 모아야 해요",
    "img": "/img/jsparrow/seed0.png"
  },{
    "msg": "보통 난이도를 해결하면 먹이 1개를",
    "img": "/img/guide/normal.png"
  },{
    "msg": "어려운 난이도를 해결하면 먹이 2개를 얻을 수 있어요",
    "img": "/img/guide/hard.png"
  },{
    "msg": "먹이 15개를 모으고 아기새들에게 가보아요",
    "img": "/img/jsparrow/baby0.png",
    "x" : 27,
    "y" : 4
  },{
    "msg": "다음버튼 혹은 아무곳이나 눌러 코딩을 시작하세요",
    "x" : 8,
    "y" : 3
  }]
}
