{

  "tile_size":256,
  "score":3,
  "workspace": ["start"],
  "toolbox": [
    "move_up",
    "move_down",
    "move_right",
    "move_left",
    "repeat",
    "get_item",
    "use_item"
  ],

  "map": [
    ".#######.",
    "#C#.#J.##",
    "#...#..##",
    "##.c#p.##",
    "##......#",
    "#.)##..v#",
    "#....u..#",
    "##.####.#",
    ".#%gik##."
  ],
  "extra":[{
    "x": 2,
    "y": 8,
    "img":"question",
    "useItem": true
  },{
    "x": 2,
    "y": 5,
    "img":"green3"
  }],
  "tutorial": [{
    "msg:ko": "'?'에 들어갈 색을 가져와요'",
    "msg:en": "Let's find color to fill the ? space and put it there",
    "img": ["/img/b7_w2/question.png","/img/blocks/bring.png","/img/blocks/use.png"]
  }]
}
